[
    {"name": "homekit", "group": "communication"},
    {"name": "house.circle", "group": "communication"},
    {"name": "mic", "group": "communication"},
    {"name": "heart", "group": "communication"},
    {"name": "heart.fill", "group": "communication"},
    {"name": "bolt.heart", "group": "communication"},
    {"name": "mic.fill", "group": "communication"},
    {"name": "rectangle.and.pencil.and.ellipsis", "group": "communication"},
    {"name": "mic.badge.plus", "group": "communication"},
    {"name": "mic.fill.badge.plus", "group": "communication"},
    {"name": "mic.and.signal.meter", "group": "communication"},
    {"name": "message", "group": "communication"},
    {"name": "message.and.waveform", "group": "communication"},
    {"name": "checkmark.message", "group": "communication"},
    {"name": "plus.message", "group": "communication"},
    {"name": "ellipsis.message", "group": "communication"},
    {"name": "exclamationmark.bubble", "group": "communication"},
    {"name": "exclamationmark.bubble.fill", "group": "communication"},
    {"name": "text.bubble", "group": "communication"},
    {"name": "text.bubble.fill", "group": "communication"},
    {"name": "info.bubble", "group": "communication"},
    {"name": "info.bubble.fill", "group": "communication"},
    {"name": "questionmark.bubble", "group": "communication"},
    {"name": "questionmark.bubble.fill", "group": "communication"},
    {"name": "plus.bubble", "group": "communication"},
    {"name": "plus.bubble.fill", "group": "communication"},
    {"name": "checkmark.bubble", "group": "communication"},
    {"name": "checkmark.bubble.fill", "group": "communication"},
    {"name": "phone.bubble.left", "group": "communication"},
    {"name": "phone.bubble.left.fill", "group": "communication"},
    {"name": "video.bubble.left", "group": "communication"},
    {"name": "video.bubble.left.fill", "group": "communication"},
    {"name": "bubble.left.and.bubble.right", "group": "communication"},
    {"name": "bubble.left.and.bubble.right.fill", "group": "communication"},
    {"name": "phone", "group": "communication"},
    {"name": "phone.fill", "group": "communication"},
    {"name": "phone.arrow.up.right", "group": "communication"},
    {"name": "phone.arrow.up.right.fill", "group": "communication"},
    {"name": "phone.arrow.down.left", "group": "communication"},
    {"name": "phone.arrow.down.left.fill", "group": "communication"},
    {"name": "video", "group": "communication"},
    {"name": "video.fill", "group": "communication"},
    {"name": "envelope", "group": "communication"},
    {"name": "envelope.fill", "group": "communication"},
    {"name": "sun.max", "group": "weather"},
    {"name": "sun.max.fill", "group": "weather"},
    {"name": "sun.max.circle", "group": "weather"},
    {"name": "sun.max.circle.fill", "group": "weather"},
    {"name": "sun.dust", "group": "weather"},
    {"name": "sun.dust.fill", "group": "weather"},
    {"name": "sun.haze", "group": "weather"},
    {"name": "sun.haze.fill", "group": "weather"},
    {"name": "moon", "group": "weather"},
    {"name": "moon.fill", "group": "weather"},
    {"name": "moon.stars", "group": "weather"},
    {"name": "moon.stars.fill", "group": "weather"},
    {"name": "cloud", "group": "weather"},
    {"name": "cloud.fill", "group": "weather"},
    {"name": "cloud.drizzle", "group": "weather"},
    {"name": "cloud.drizzle.fill", "group": "weather"},
    {"name": "cloud.rain", "group": "weather"},
    {"name": "cloud.rain.fill", "group": "weather"},
    {"name": "cloud.snow", "group": "weather"},
    {"name": "cloud.snow.fill", "group": "weather"},
    {"name": "cloud.bolt.rain", "group": "weather"},
    {"name": "cloud.bolt.rain.fill", "group": "weather"},
    {"name": "cloud.sun", "group": "weather"},
    {"name": "cloud.sun.fill", "group": "weather"},
    {"name": "snowflake", "group": "weather"},
    {"name": "snowflake.circle", "group": "weather"},
    {"name": "snowflake.circle.fill", "group": "weather"},
    {"name": "tropicalstorm", "group": "weather"},
    {"name": "tropicalstorm.circle", "group": "weather"},
    {"name": "hurricane", "group": "weather"},
    {"name": "thermometer.snowflake", "group": "weather"},
    {"name": "humidity", "group": "weather"},
    {"name": "humidity.fill", "group": "weather"},
    {"name": "carbon.dioxide.cloud", "group": "weather"},
    {"name": "carbon.dioxide.cloud.fill", "group": "weather"},
    {"name": "person", "group": "human"},
    {"name": "person.fill", "group": "human"},
    {"name": "person.badge.key", "group": "human"},
    {"name": "person.badge.key.fill", "group": "human"},
    {"name": "person.badge.shield.checkmark", "group": "human"},
    {"name": "person.badge.shield.checkmark.fill", "group": "human"},
    {"name": "rectangle.inset.filled.and.person.filled", "group": "human"},
    {"name": "shared.with.you", "group": "human"},
    {"name": "person.2", "group": "human"},
    {"name": "person.2.fill", "group": "human"},
    {"name": "person.3", "group": "human"},
    {"name": "person.3.fill", "group": "human"},
    {"name": "person.text.rectangle.fill", "group": "human"},
    {"name": "figure.dress.line.vertical.figure", "group": "human"},
    {"name": "figure.2.and.child.holdinghands", "group": "human"},
    {"name": "figure.mind.and.body", "group": "human"},
    {"name": "figure.outdoor.cycle", "group": "human"},
    {"name": "lungs", "group": "human"},
    {"name": "lungs.fill", "group": "human"},
    {"name": "tshirt", "group": "human"},
    {"name": "tshirt.fill", "group": "human"},
    {"name": "face.smiling", "group": "human"},
    {"name": "face.smiling.inverse", "group": "human"},
    {"name": "eye", "group": "human"},
    {"name": "eye.fill", "group": "human"},
    {"name": "eyes", "group": "human"},
    {"name": "eyes.inverse", "group": "human"},
    {"name": "mouth", "group": "human"},
    {"name": "mouth.fill", "group": "human"},
    {"name": "hand.raised.fingers.spread", "group": "human"},
    {"name": "hand.raised.fingers.spread.fill", "group": "human"},
    {"name": "hand.thumbsup", "group": "human"},
    {"name": "hand.thumbsup.fill", "group": "human"},
    {"name": "hand.point.up.braille", "group": "human"},
    {"name": "hand.point.up.braille.fill", "group": "human"},
    {"name": "hands.clap", "group": "human"},
    {"name": "hands.clap.fill", "group": "human"},
    {"name": "hands.sparkles", "group": "human"},
    {"name": "hands.sparkles.fill", "group": "human"},
    
    {"name": "pencil" ,"group": "object"},
    {"name": "rectangle.and.pencil.and.ellipsis","group": "object"},
    {"name": "highlighter","group": "object"},
    {"name": "pencil.tip","group": "object"},
    {"name": "lasso.and.sparkles","group": "object"},
    {"name": "trash","group": "object"},
    {"name": "folder.fill","group": "object"},
    {"name": "folder.badge.plus","group": "object"},
    {"name": "folder.fill.badge.plus","group": "object"},
    {"name": "square.grid.3x1.folder.badge.plus","group": "object"},
    {"name": "square.grid.3x1.folder.fill.badge.plus","group": "object"},
    {"name": "paperplane","group": "object"},
    {"name": "paperplane.fill","group": "object"},
    {"name": "list.bullet.clipboard","group": "object"},
    {"name": "list.bullet.clipboard.fill","group": "object"},
    {"name": "doc.text.magnifyingglass","group": "object"},
    {"name": "note.text.badge.plus","group": "object"},
    {"name": "calendar.badge.clock","group": "object"},
    {"name": "calendar.badge.exclamationmark","group": "object"},
    {"name": "book.fill","group": "object"},
    {"name": "books.vertical","group": "object"},
    {"name": "books.vertical.fill","group": "object"},
    {"name": "menucard","group": "object"},
    {"name": "menucard.fill","group": "object"},
    {"name": "bookmark","group": "object"},
    {"name": "bookmark.fill","group": "object"},
    {"name": "graduationcap","group": "object"},
    {"name": "graduationcap.fill","group": "object"},
    {"name": "pencil.and.ruler","group": "object"},
    {"name": "pencil.and.ruler.fill","group": "object"},
    {"name": "paperclip","group": "object"},
    {"name": "rectangle.dashed.and.paperclip","group": "object"},
    {"name": "link","group": "object"},
    {"name": "personalhotspot","group": "object"},
    {"name": "dumbbell","group": "object"},
    {"name": "dumbbell.fill","group": "object"},
    {"name": "soccerball","group": "object"},
    {"name": "soccerball.inverse","group": "object"},
    {"name": "baseball","group": "object"},
    {"name": "baseball.fill","group": "object"},
    {"name": "basketball","group": "object"},
    {"name": "basketball.fill","group": "object"},
    {"name": "football","group": "object"},
    {"name": "football.fill","group": "object"},
    {"name": "tennis.racket","group": "object"},
    {"name": "hockey.puck","group": "object"},
    {"name": "hockey.puck.fill","group": "object"},
    {"name": "cricket.ball","group": "object"},
    {"name": "cricket.ball.fill","group": "object"},
    {"name": "tennisball","group": "object"},
    {"name": "tennisball.fill","group": "object"},
    {"name": "volleyball","group": "object"},
    {"name": "volleyball.fill","group": "object"},
    {"name": "trophy","group": "object"},
    {"name": "trophy.fill","group": "object"},
    {"name": "medal","group": "object"},
    {"name": "medal.fill","group": "object"},
    {"name": "umbrella","group": "object"},
    {"name": "umbrella.fill","group": "object"},
    {"name": "megaphone","group": "object"},
    {"name": "megaphone.fill","group": "object"},
    {"name": "speaker.zzz","group": "object"},
    {"name": "speaker.zzz.fill","group": "object"},
    {"name": "magnifyingglass","group": "object"},
    {"name": "plus.magnifyingglass","group": "object"},
    {"name": "minus.magnifyingglass","group": "object"},
    {"name": "sparkle.magnifyingglass","group": "object"},
    {"name": "flag","group": "object"},
    {"name": "flag.2.crossed","group": "object"},
    {"name": "flag.checkered.2.crossed","group": "object"},
    {"name": "bell","group": "object"},
    {"name": "bell.fill","group": "object"},
    {"name": "bell.slash","group": "object"},
    {"name": "bell.slash.fill","group": "object"},
    {"name": "camera","group": "object"},
    {"name": "camera.fill","group": "object"},
    {"name": "gearshape","group": "object"},
    {"name": "scissors","group": "object"},
    {"name": "bag","group": "object"},
    {"name": "bag.fill","group": "object"},
    {"name": "cart","group": "object"},
    {"name": "basket","group": "object"},
    {"name": "creditcard","group": "object"},
    {"name": "creditcard.fill","group": "object"},
    {"name": "wand.and.rays.inverse","group": "object"},
    {"name": "wand.and.stars","group": "object"},
    {"name": "gyroscope","group": "object"},
    {"name": "gauge.medium","group": "object"},
    {"name": "amplifier","group": "object"},
    {"name": "pianokeys","group": "object"},
    {"name": "pianokeys.inverse","group": "object"},
    {"name": "paintbrush","group": "object"},
    {"name": "paintbrush.pointed","group": "object"},
    {"name": "wrench.adjustable","group": "object"},
    {"name": "screwdriver","group": "object"},
    {"name": "wrench.and.screwdriver","group": "object"},
    {"name": "stethoscope","group": "object"},
    {"name": "printer","group": "object"},
    {"name": "briefcase","group": "object"},
    {"name": "latch.2.case.fill","group": "object"},
    {"name": "cross.case","group": "object"},
    {"name": "suitcase.cart","group": "object"},
    {"name": "theatermasks","group": "object"},
    {"name": "theatermask.and.paintbrush","group": "object"},
    {"name": "puzzlepiece","group": "object"},
    {"name": "lightbulb.led","group": "object"},
    {"name": "fanblades","group": "object"},
    {"name": "fan.and.light.ceiling","group": "object"},
    {"name": "lamp.desk","group": "object"},
    {"name": "lamp.table","group": "object"},
    {"name": "lamp.ceiling","group": "object"},
    {"name": "frying.pan","group": "object"},
    {"name": "sofa","group": "object"},
    {"name": "chair","group": "object"},
    {"name": "toilet","group": "object"},
    {"name": "lock","group": "object"},
    {"name": "lock.circle","group": "object"},
    {"name": "exclamationmark.lock","group": "object"},
    {"name": "lock.open","group": "object"},
    {"name": "key","group": "object"},
    {"name": "pin","group": "object"},
    {"name": "mappin.and.ellipse","group": "object"},
    {"name": "powerplug","group": "object"},
    {"name": "airpodsmax","group": "object"},
    {"name": "fuelpump","group": "object"},
    {"name": "bandage","group": "object"},
    {"name": "syringe","group": "object"},
    {"name": "facemask","group": "object"},
    {"name": "film.stack","group": "object"},
    {"name": "eyeglasses","group": "object"},
    {"name": "crown","group": "object"},
    {"name": "cube","group": "object"},
    {"name": "clock","group": "object"},
    {"name": "deskclock","group": "object"},
    {"name": "alarm.waves.left.and.right.fill","group": "object"},
    {"name": "gamecontroller","group": "object"},
    {"name": "paintpalette","group": "object"},
    {"name": "cup.and.saucer","group": "object"},
    {"name": "cup.and.saucer.fill","group": "object"},
    {"name": "takeoutbag.and.cup.and.straw","group": "object"},
    {"name": "birthday.cake","group": "object"},
    {"name": "birthday.cake.fill","group": "object"},
    {"name": "carrot","group": "object"},
    {"name": "carrot.fill","group": "object"},
    {"name": "fork.knife","group": "object"},
    {"name": "gift","group": "object"},
    {"name": "gift.fill","group": "object"},
    {"name": "hourglass","group": "object"},
    {"name": "hourglass.bottomhalf.filled","group": "object"},
    {"name": "hourglass.tophalf.filled","group": "object"},
    {"name": "camera.filters","group": "object"},
    {"name": "binoculars","group": "object"},
    {"name": "battery.100","group": "object"},
    {"name": "camera.on.rectangle","group": "object"},
    {"name": "camera.macro","group": "object"},
    {"name": "photo","group": "object"},
    {"name": "square.3.layers.3d","group": "object"},
    {"name": "square.3.layers.3d.top.filled","group": "object"}
    
]


